src/__init__.py
src/api.py
src/auth.py
src/auth_helper.py
src/thunder.py
src/thunder_helper.py
src/watchdog.py
thunder/__init__.py
thunder/api.py
thunder/auth.py
thunder/auth_helper.py
thunder/get_latest.py
thunder/thunder.py
thunder/thunder_helper.py
thunder/watchdog.py
thunder_cli-1.1.5.dist-info/LICENSE
thunder_cli-1.1.5.dist-info/METADATA
thunder_cli-1.1.5.dist-info/WHEEL
thunder_cli-1.1.5.dist-info/entry_points.txt
thunder_cli-1.1.5.dist-info/top_level.txt
thunder_cli-1.1.5.dist-info/RECORD
