Metadata-Version: 2.1
Name: thunder-cli
Version: 1.1.5
License-File: LICENSE
Requires-Dist: Click
Requires-Dist: requests
Requires-Dist: cryptography
Requires-Dist: common
